sdg_dev/__init__.py
sdg_dev/dev_async.py
sdg_dev/dev_common.py
sdg_dev/dev_err.py
sdg_dev/dev_master.py
sdg_dev/example.py
sdg_dev/protocol.py
sdg_dev/tests.py
sdg_dev/__pycache__/__init__.cpython-310.pyc
sdg_dev/__pycache__/dev_async.cpython-310.pyc
sdg_dev/__pycache__/dev_err.cpython-310.pyc
sdg_dev/__pycache__/dev_master.cpython-310.pyc
sdg_dev/__pycache__/protocol.cpython-310.pyc
sdg_dev-2.7.dist-info/LICENSE
sdg_dev-2.7.dist-info/METADATA
sdg_dev-2.7.dist-info/WHEEL
sdg_dev-2.7.dist-info/top_level.txt
sdg_dev-2.7.dist-info/RECORD
