Metadata-Version: 2.1
Name: sdg-dev
Version: 2.7
Summary: master and slave over sdg_io
Author: chernecov_ev
Author-email: chernecov.ev@gmail.com
Classifier: Programming Language :: Python :: 3
Classifier: License :: OSI Approved :: MIT License
Classifier: Operating System :: OS Independent
Requires-Python: >=3.6
License-File: LICENSE
Requires-Dist: sdg-io >=3.0
Requires-Dist: sdg-utils >=1.0
